flavorfetcher/__init__.py
flavorfetcher/datamunging.py
flavorfetcher/descriptor_model.py
flavorfetcher/makepredictions.py
flavorfetcher/data/100_2021-04-20 10_38_24.203316_3_epochs_re-run_model.h5
flavorfetcher/data/100_2021-04-20 10_38_24.203316_3_epochs_re-run_model.json
flavorfetcher/data/Example Whiskey Reviews.csv
flavorfetcher/data/__init__.py
flavorfetcher-1.0.0.dist-info/LICENSE
flavorfetcher-1.0.0.dist-info/METADATA
flavorfetcher-1.0.0.dist-info/WHEEL
flavorfetcher-1.0.0.dist-info/top_level.txt
flavorfetcher-1.0.0.dist-info/RECORD
