Metadata-Version: 2.1
Name: flavorfetcher
Version: 1.0.0
Summary: Python code to identify flavor-descriptors in natural language English text using a pre-trained LSTM. https://doi.org/10.3390/foods10071633
Author-email: Chreston Miller <chmille3@vt.edu>, Leah Hamilton <leah.hamilton0@gmail.com>
Maintainer-email: Leah Hamilton <leah.hamilton0@gmail.com>
License: GNU GENERAL PUBLIC LICENSE
Project-URL: Homepage, https://github.com/lhami/flavor-fetcher
Project-URL: Bug Tracker, https://github.com/lhami/flavor-fetcher/issues
Classifier: Programming Language :: Python :: 3
Classifier: License :: OSI Approved :: GNU General Public License v3 or later (GPLv3+)
Classifier: Operating System :: OS Independent
Classifier: Intended Audience :: Science/Research
Requires-Python: >=3.7
License-File: LICENSE
Requires-Dist: numpy
Requires-Dist: keras (>=2.3)
Requires-Dist: pandas
Requires-Dist: tensorflow (>=2)
